mdrun/SchedulingEngine.py
mdrun/Simulation.py
mdrun/__init__.py
mdrun/cli.py
mdrun/bin/launch_PBS_jobs
mdrun/data/input_example.json
mdrun/tests/__init__.py
mdrun/tests/test_CommandLineInterface.py
mdrun/tests/test_Simulation.py
mdrun-0.1.5.data/scripts/launch_PBS_jobs
mdrun-0.1.5.dist-info/DESCRIPTION.rst
mdrun-0.1.5.dist-info/METADATA
mdrun-0.1.5.dist-info/RECORD
mdrun-0.1.5.dist-info/WHEEL
mdrun-0.1.5.dist-info/entry_points.txt
mdrun-0.1.5.dist-info/metadata.json
mdrun-0.1.5.dist-info/top_level.txt
