Metadata-Version: 2.0
Name: mdrun
Version: 0.1.5
Summary: Submission of MD runs to HPC with PBS
Home-page: https://github.com/jeiros/mdrun
Author: Juan Eiros
Author-email: jeirosz@gmail.com
License: MIT license
Download-URL: https://github.com/jeiros/mdrun/archive/0.1.5.tar.gz
Keywords: MD
Platform: UNKNOWN
Classifier: Development Status :: 2 - Pre-Alpha
Classifier: Intended Audience :: Developers
Classifier: License :: OSI Approved :: MIT License
Classifier: Natural Language :: English
Classifier: Programming Language :: Python :: 3
Classifier: Programming Language :: Python :: 3.3
Classifier: Programming Language :: Python :: 3.4
Classifier: Programming Language :: Python :: 3.5
Requires-Dist: Click (>=6.0)
